LICENSE
README.md
setup.py
esfores/__init__.py
esfores/forchan.py
forchan.egg-info/PKG-INFO
forchan.egg-info/SOURCES.txt
forchan.egg-info/dependency_links.txt
forchan.egg-info/entry_points.txt
forchan.egg-info/requires.txt
forchan.egg-info/top_level.txt