Metadata-Version: 2.1
Name: forchan
Version: 1.1.1
Summary: Check your fortune as is tradition on [s4s].
Home-page: https://github.com/ganelonhb/forchan
Author: ganelon
License: GPLv3+
Keywords: fortune forchan fourchan 4chan s4s esfores kek jej zozzle
Platform: UNKNOWN
Classifier: Development Status :: 4 - Beta
Classifier: Environment :: Console
Classifier: Intended Audience :: Other Audience
Classifier: License :: OSI Approved :: GNU General Public License v3 or later (GPLv3+)
Classifier: Natural Language :: English
Classifier: Operating System :: OS Independent
Classifier: Programming Language :: Python
Classifier: Programming Language :: Python :: 3.10
Classifier: Topic :: Games/Entertainment :: Fortune Cookies
License-File: LICENSE
